setup.py
bdd/__init__.py
bdd/manage.py
blood_donors_directory.egg-info/PKG-INFO
blood_donors_directory.egg-info/SOURCES.txt
blood_donors_directory.egg-info/dependency_links.txt
blood_donors_directory.egg-info/top_level.txt