Metadata-Version: 1.1
Name: blood-donors-directory
Version: 0.0.2
Summary: A web application to maintain blood donors database
Home-page: https://github.com/akhilputhiry/blood-donors-directory
Author: Akhil Lawrence
Author-email: akhilputhiry@gmail.com
License: GNU GPLv3
Keywords: blood donation
Platform: UNKNOWN
Classifier: Development Status :: 1 - Planning
Classifier: Topic :: Internet :: WWW/HTTP
Classifier: Programming Language :: Python :: 2.7
Classifier: License :: Freeware
